polygon_data/__init__.py
polygon_data/data_process.py
DE_FOREX_Library-0.0.4.dist-info/METADATA
DE_FOREX_Library-0.0.4.dist-info/WHEEL
DE_FOREX_Library-0.0.4.dist-info/top_level.txt
DE_FOREX_Library-0.0.4.dist-info/RECORD
