Metadata-Version: 2.1
Name: DE-FOREX-Library
Version: 0.0.4
Summary: Demo library
Home-page: https://de-forex-library.readthedocs.io/
Author: Tianyi Wu
Author-email: tw2709@nyu.edu
License: MIT
Classifier: Intended Audience :: Developers
Classifier: License :: OSI Approved :: MIT License
Classifier: Programming Language :: Python
Classifier: Programming Language :: Python :: 3
Classifier: Programming Language :: Python :: 3.6
Classifier: Programming Language :: Python :: 3.7
Classifier: Programming Language :: Python :: 3.8
Classifier: Programming Language :: Python :: 3.9
Classifier: Operating System :: OS Independent
Requires-Dist: polygon-api-client (==0.2.11)
